emg_feature_extraction/__init__.py
tests/__init__.py
tests/test_feature_extractor.py
unb_emg_toolbox/__init__.py
unb_emg_toolbox/feature_extractor.py
unb_emg_toolbox-0.0.2.dist-info/LICENSE
unb_emg_toolbox-0.0.2.dist-info/METADATA
unb_emg_toolbox-0.0.2.dist-info/WHEEL
unb_emg_toolbox-0.0.2.dist-info/top_level.txt
unb_emg_toolbox-0.0.2.dist-info/RECORD
