Metadata-Version: 2.1
Name: unb-emg-toolbox
Version: 0.0.2
Summary: Extract Features
Home-page: UNKNOWN
Author: Ethan & Evan
License: UNKNOWN
Keywords: emg,feature_extraction,pattern_recognition
Platform: UNKNOWN
Classifier: Development Status :: 1 - Planning
Classifier: Intended Audience :: Developers
Classifier: Programming Language :: Python :: 3
Classifier: Operating System :: Unix
Classifier: Operating System :: MacOS :: MacOS X
Classifier: Operating System :: Microsoft :: Windows
License-File: LICENSE
Requires-Dist: numpy
Requires-Dist: scipy
Requires-Dist: sampen
